impl_v2/datapath/gpr.v
module gpr(
    input [4:0] ra,
    input [4:0] rb,
    input [4:0] rw,
    input [31:0] wd3,
    input clk,
    input we3,
    output reg [31:0] rd1,
    output reg [31:0] rd2
);
    reg [31:0] reg32 [31:0]; // 定义32个32位寄存器
    reg [31:0] R0, R1, R2, R3, R4, R5, R6, R7, R8, R9, R10, R11, R12;

    initial begin
        $readmemb("register.txt", reg32,0,31); // 从文件中读取寄存器初始值
        //$readmemb("../register.txt", reg32); // 从文件中读取寄存器初始值
    end
    always @(*) begin
        rd1 <= reg32[ra]; // 读取操作1
        rd2 <= reg32[rb]; // 读取操作2
        reg32[0] <= 0;

        //输出显示
        R0 <= reg32[0];
        R1 <= reg32[1];
        R2 <= reg32[2];
        R3 <= reg32[3];
        R4 <= reg32[4];
        R5 <= reg32[5];
        R6 <= reg32[6];
        R7 <= reg32[7];
        R8 <= reg32[8];
        R9 <= reg32[9];
        R10 <= reg32[10];
        R11 <= reg32[11];
        R12 <= reg32[12];

    end
    always @(posedge clk) begin
        if (we3) begin
            reg32[rw] <= wd3; // 写入操作
        end
        $writememb("register_after.txt", reg32,0,31);
    end

endmodule

impl_v2/datapath/alu.v
module alu(
    input [31:0] srcA,
    input [31:0] srcB,
    input [2:0] ctrl,
    output reg zero,
    output reg [31:0] aluResu
);

always @(*) begin
    case (ctrl)
        3'b000: aluResu = srcA + srcB; // ADD operation
        3'b001: aluResu = srcA - srcB; // SUB operation
        3'b010: aluResu = srcA & srcB; // AND operation
        3'b011: aluResu = srcA | srcB; // OR operation
        default: aluResu = 32'b0; // Default case
    endcase
    
    // Set zero flag
    if (aluResu == 32'b0)
        zero = 1;
    else
        zero = 0;
end

endmodule

impl_v2/datapath/ext.v
module ext(
    input [15:0] data16,
    input [1:0] ext_op,
    output reg [31:0] data32
);

always @(*) begin
    if (ext_op == 2'b00) begin
        data32 <= {16'b0, data16}; // 零扩展
    end else if(ext_op == 2'b01) begin
        data32 <= {{16{data16[15]}}, data16}; // 符号扩展
    end else begin
        data32 <= {data16,16'b0}; // lui扩展
    end
end

endmodule

impl_v2/datapath/mux32.v
module mux32(
    input sel,
    input [31:0] a,
    input [31:0] b,
    output reg [31:0] c
);

always @(*) begin
    if (sel == 0) begin
        c <= a;
    end else begin
        c <= b;
    end
end

endmodule

impl_v2/datapath/mux5.v
module mux5(
    input sel,
    input [4:0] a,
    input [4:0] b,
    output reg [4:0] c
);

always @(*) begin
    if (sel == 0) begin
        c <= a;
    end else begin
        c <= b;
    end
end

endmodule

impl_v2/datapath/dm.v
module dm(
    input [31:0] addr,
    input [31:0] wd,        //write address
    input wrEn,               //write enable
    input clk,              
    output reg [31:0] rd
);

    reg [31:0] dataMem [255:0]; // 定义256个32位的数据存储器
    initial begin
        //$readmemb("../data.txt", dataMem); // 从文件中读取数据初始值
        $readmemb("data.txt", dataMem,0,255); // 从文件中读取数据初始值
    end

    always @(*) begin
        rd <= dataMem[addr[31:2]]; // 读取操作
    end

    always @(posedge clk) begin
        if (wrEn == 1) begin
            dataMem[addr[31:2]] <= wd; // 使用 `addr` 作为地址，`wd` 作为数据
        end
        $writememb("data_after.txt", dataMem,0,255);
    end

endmodule

impl_v2/datapath/im.v
module im(
    input [31:0] addr,
    output reg [31:0] instr
);
    reg [7:0] memory [0:1023]; // 1KB = 1024 bytes
    initial begin
        //$readmemb("../code.txt", memory);
        $readmemh("code.txt", memory, 0, 1023);
    end

    always @(*) begin
        // 拼接四个字节成一个32位指令
        instr <= {memory[addr], memory[addr + 1], memory[addr + 2], memory[addr+3]};
    end
    
endmodule

impl_v2/datapath/ifu.v
`include "datapath/im.v"

module ifu(
    input [31:0] imm32, // 输入的跳转立即数，需要经过ext32
    input clk,
    input reset,
    input zero,
    input [1:0] nPC_sel,
    input [25:0] imm26,
    output reg [31:0] pc,
    output wire [31:0] instr // 将instr声明为wire类型
);
    initial begin
        pc <= 32'b0; // default pc as start
    end
    
    // 实例化指令存储器模块
    im IM(
        .addr(pc),
        .instr(instr)
    );

    always @(posedge clk or posedge reset) begin
        if (reset) begin
            pc <= 32'b0; // 复位时将PC置为0
        end else begin
            case (nPC_sel)
                2'b01: begin
                    if (zero) begin
                        pc <= pc + 4 + (imm32 << 2); // 条件满足时PC加立即数
                    end else begin
                        pc <= pc + 4; // 否则PC加4
                    end
                end
                2'b10: begin
                    pc <= {pc[31:28], imm26, 2'b00}; // 跳转地址
                end
                default: begin
                    pc <= pc + 4; // 否则PC加4
                end
            endcase
        end
    end
endmodule

impl_v2/datapath/divider.v
module divider(
    input [31:0] instr,
    output reg [5:0] opcode,
    output reg [4:0] rs,
    output reg [4:0] rt,
    output reg [4:0] rd,
    output reg [4:0] shamt,
    output reg [5:0] funct,
    output reg [15:0] imm16,
    output reg [25:0] imm26
);
    always @(*) begin
        opcode = instr[31:26]; // 操作码：位31到位26
        rs     = instr[25:21]; // 源寄存器：位25到位21
        rt     = instr[20:16]; // 目标寄存器：位20到位16
        rd     = instr[15:11]; // 目的寄存器：位15到位11
        shamt  = instr[10:6];  // 移位量：位10到位6
        funct  = instr[5:0];   // 功能码：位5到位0
        imm16  = instr[15:0];  // 立即数：位15到位0
        imm26  = instr[25:0];  //跳转数：位25到位0
    end
endmodule

impl_v2/control/ctrl.v
module ctrl(
    input [5:0] op,
    input [5:0] funct,
    output reg mem2Reg, 
    output reg memWrite, 
    output reg aluSrc, 
    output reg regDst, 
    output reg regWrite, 
    output reg [1:0] nPC_sel, 
    output reg pcReset,
    output reg [1:0] ext_op,
    output reg [2:0] aluCtr
);
    reg [12:0] tempcode;
    
    always @(*) begin
        // 默认值
        tempcode = 13'b0;

        // 根据 op 和 funct 设置 tempcode
        if (op == 6'b000000) begin // R 型指令
            case (funct)
                6'b100001: tempcode = 13'b0000000011000; // ADDU
                6'b100011: tempcode = 13'b0010000011000; // SUBU
                default: tempcode = 13'b0;
            endcase
        end else begin
            case (op)
                6'b001101: tempcode = 13'b0110000010100; // ORI
                6'b100011: tempcode = 13'b0000100010101; //LW
                6'b101011: tempcode = 13'b0000100001110; //SW
                6'b000100: tempcode = 13'b0010000100000; //BEQ
                6'b000010: tempcode = 13'b0000001000000; //j
                6'b001111: tempcode = 13'b0001000010100; //lui
                default: tempcode = 13'b0;
            endcase
        end
        {aluCtr, ext_op, pcReset, nPC_sel, regWrite, regDst, aluSrc, memWrite, mem2Reg} = tempcode;
    end

endmodule

impl_v2/mips.v
`include "datapath/gpr.v"
`include "datapath/alu.v"
`include "datapath/ext.v"
`include "datapath/mux32.v"
`include "datapath/mux5.v"
`include "datapath/dm.v"
`include "datapath/ifu.v"
`include "datapath/divider.v"
`include "control/ctrl.v"
`timescale 1ns / 1ps

module mips();

reg clk;

initial begin
    clk = 0;
    forever #5 clk = ~clk; // 时钟周期为10ns
end



// 内部连接信号声明
wire [31:0] instr;
wire [31:0] imm32;
wire [5:0] opcode, funct;
wire [4:0] rs, rt, rd, shamt, rw;
wire [15:0] imm16;
wire [2:0] aluCtr;
wire [1:0] nPC_sel, ext_op;
wire mem2Reg, memWrite, aluSrc, regDst, regWrite, zero, pcReset;
wire [31:0] pc, dmData, BusA, BusB, BusW, BusW2, BusB2;
wire [25:0] imm26;

//实例化全部模块
ctrl CTRL (
    .op(opcode),
    .funct(funct),
    .mem2Reg(mem2Reg),
    .memWrite(memWrite),
    .aluSrc(aluSrc),
    .regDst(regDst),
    .regWrite(regWrite),
    .aluCtr(aluCtr),
    .nPC_sel(nPC_sel),
    .pcReset(pcReset),
    .ext_op(ext_op)

);
divider DIV (
    .instr(instr),
    .opcode(opcode),
    .rs(rs),
    .rt(rt),
    .rd(rd),
    .shamt(shamt),
    .funct(funct),
    .imm16(imm16),
    .imm26(imm26)
);
ifu IFU(
    .imm32(imm32),
    .clk(clk),
    .reset(pcReset),
    .zero(zero),
    .nPC_sel(nPC_sel),
    .pc(pc), //输出PC连接Pc显示
    .instr(instr),
    .imm26(imm26)
);
dm DM (
    .addr(BusW),
    .wrEn(memWrite),
    .clk(clk),
    .wd(BusB),
    .rd(dmData) //连接Mem2RegMux选择读取Data字
);
mux32 Mem2RegMux (
    .sel(mem2Reg),
    .a(BusW),
    .b(dmData),
    .c(BusW2) //连接到GPR的rw
);
mux5 RegMux (
    .sel(regDst),
    .a(rt),
    .b(rd),
    .c(rw) //连接到GPR的rw
);
mux32 ALUSrcMux (
    .sel(aluSrc),
    .a(BusB),
    .b(imm32),
    .c(BusB2) //连接ALU的BusB输入
);
ext EXT (
    .data16(imm16),
    .ext_op(ext_op),
    .data32(imm32)
);
alu ALU (
    .srcA(BusA),
    .srcB(BusB2),
    .ctrl(aluCtr),
    .zero(zero),
    .aluResu(BusW)
);
gpr GPR (
    .ra(rs),
    .rb(rt),
    .rw(rw),
    .wd3(BusW2),
    .clk(clk),
    .we3(regWrite),
    .rd1(BusA),
    .rd2(BusB)
);
initial begin
    $dumpfile("mips_tb.vcd");
    $dumpvars(0, mips);
    #200;
    $finish;
end

endmodule

impl_v2/mips_tb.vcd
$date
	Tue May 21 20:11:31 2024
$end
$version
	Icarus Verilog
$end
$timescale
	1ps
$end
$scope module mips $end
$var wire 1 ! zero $end
$var wire 5 " shamt [4:0] $end
$var wire 5 # rw [4:0] $end
$var wire 5 $ rt [4:0] $end
$var wire 5 % rs [4:0] $end
$var wire 1 & regWrite $end
$var wire 1 ' regDst $end
$var wire 5 ( rd [4:0] $end
$var wire 1 ) pcReset $end
$var wire 32 * pc [31:0] $end
$var wire 6 + opcode [5:0] $end
$var wire 2 , nPC_sel [1:0] $end
$var wire 1 - memWrite $end
$var wire 1 . mem2Reg $end
$var wire 32 / instr [31:0] $end
$var wire 32 0 imm32 [31:0] $end
$var wire 26 1 imm26 [25:0] $end
$var wire 16 2 imm16 [15:0] $end
$var wire 6 3 funct [5:0] $end
$var wire 2 4 ext_op [1:0] $end
$var wire 32 5 dmData [31:0] $end
$var wire 1 6 aluSrc $end
$var wire 3 7 aluCtr [2:0] $end
$var wire 32 8 BusW2 [31:0] $end
$var wire 32 9 BusW [31:0] $end
$var wire 32 : BusB2 [31:0] $end
$var wire 32 ; BusB [31:0] $end
$var wire 32 < BusA [31:0] $end
$var reg 1 = clk $end
$scope module ALU $end
$var wire 32 > srcB [31:0] $end
$var wire 32 ? srcA [31:0] $end
$var wire 3 @ ctrl [2:0] $end
$var reg 32 A aluResu [31:0] $end
$var reg 1 ! zero $end
$upscope $end
$scope module ALUSrcMux $end
$var wire 1 6 sel $end
$var wire 32 B b [31:0] $end
$var wire 32 C a [31:0] $end
$var reg 32 D c [31:0] $end
$upscope $end
$scope module CTRL $end
$var wire 6 E op [5:0] $end
$var wire 6 F funct [5:0] $end
$var reg 3 G aluCtr [2:0] $end
$var reg 1 6 aluSrc $end
$var reg 2 H ext_op [1:0] $end
$var reg 1 . mem2Reg $end
$var reg 1 - memWrite $end
$var reg 2 I nPC_sel [1:0] $end
$var reg 1 ) pcReset $end
$var reg 1 ' regDst $end
$var reg 1 & regWrite $end
$var reg 13 J tempcode [12:0] $end
$upscope $end
$scope module DIV $end
$var wire 32 K instr [31:0] $end
$var reg 6 L funct [5:0] $end
$var reg 16 M imm16 [15:0] $end
$var reg 26 N imm26 [25:0] $end
$var reg 6 O opcode [5:0] $end
$var reg 5 P rd [4:0] $end
$var reg 5 Q rs [4:0] $end
$var reg 5 R rt [4:0] $end
$var reg 5 S shamt [4:0] $end
$upscope $end
$scope module DM $end
$var wire 32 T addr [31:0] $end
$var wire 1 = clk $end
$var wire 1 - wrEn $end
$var wire 32 U wd [31:0] $end
$var reg 32 V rd [31:0] $end
$upscope $end
$scope module EXT $end
$var wire 16 W data16 [15:0] $end
$var wire 2 X ext_op [1:0] $end
$var reg 32 Y data32 [31:0] $end
$upscope $end
$scope module GPR $end
$var wire 1 = clk $end
$var wire 5 Z ra [4:0] $end
$var wire 5 [ rb [4:0] $end
$var wire 1 & we3 $end
$var wire 32 \ wd3 [31:0] $end
$var wire 5 ] rw [4:0] $end
$var reg 32 ^ R0 [31:0] $end
$var reg 32 _ R1 [31:0] $end
$var reg 32 ` R10 [31:0] $end
$var reg 32 a R11 [31:0] $end
$var reg 32 b R12 [31:0] $end
$var reg 32 c R2 [31:0] $end
$var reg 32 d R3 [31:0] $end
$var reg 32 e R4 [31:0] $end
$var reg 32 f R5 [31:0] $end
$var reg 32 g R6 [31:0] $end
$var reg 32 h R7 [31:0] $end
$var reg 32 i R8 [31:0] $end
$var reg 32 j R9 [31:0] $end
$var reg 32 k rd1 [31:0] $end
$var reg 32 l rd2 [31:0] $end
$upscope $end
$scope module IFU $end
$var wire 1 = clk $end
$var wire 26 m imm26 [25:0] $end
$var wire 32 n imm32 [31:0] $end
$var wire 2 o nPC_sel [1:0] $end
$var wire 1 ) reset $end
$var wire 1 ! zero $end
$var wire 32 p instr [31:0] $end
$var reg 32 q pc [31:0] $end
$scope module IM $end
$var wire 32 r addr [31:0] $end
$var reg 32 s instr [31:0] $end
$upscope $end
$upscope $end
$scope module Mem2RegMux $end
$var wire 32 t a [31:0] $end
$var wire 32 u b [31:0] $end
$var wire 1 . sel $end
$var reg 32 v c [31:0] $end
$upscope $end
$scope module RegMux $end
$var wire 5 w a [4:0] $end
$var wire 5 x b [4:0] $end
$var wire 1 ' sel $end
$var reg 5 y c [4:0] $end
$upscope $end
$upscope $end
$enddefinitions $end
$comment Show the parameter values. $end
$dumpall
$end
#0
$dumpvars
b11 y
b0 x
b11 w
b10010011 v
bx u
b10010011 t
b110100000000110000000010010011 s
b0 r
b0 q
b110100000000110000000010010011 p
b0 o
b10010011 n
b110000000010010011 m
b0 l
b0 k
b0 j
b0 i
b0 h
b0 g
b0 f
b0 e
b0 d
b0 c
b0 b
b0 a
b0 `
b0 _
b0 ^
b11 ]
b10010011 \
b11 [
b0 Z
b10010011 Y
b0 X
b10010011 W
bx V
b0 U
b10010011 T
b10 S
b11 R
b0 Q
b0 P
b1101 O
b110000000010010011 N
b10010011 M
b10011 L
b110100000000110000000010010011 K
b110000010100 J
b0 I
b0 H
b11 G
b10011 F
b1101 E
b10010011 D
b0 C
b10010011 B
b10010011 A
b11 @
b0 ?
b10010011 >
0=
b0 <
b0 ;
b10010011 :
b10010011 9
b10010011 8
b11 7
16
bx 5
b0 4
b10011 3
b10010011 2
b110000000010010011 1
b10010011 0
b110100000000110000000010010011 /
0.
0-
b0 ,
b1101 +
b0 *
0)
b0 (
0'
1&
b0 %
b11 $
b11 #
b10 "
0!
$end
#5000
b10101110 8
b10101110 \
b10101110 v
b10101110 9
b10101110 A
b10101110 T
b10101110 t
b10101110 :
b10101110 >
b10101110 D
b10101110 0
b10101110 B
b10101110 Y
b10101110 n
b110 #
b110 ]
b110 y
b110000010100 J
b1100000000010101110 1
b1100000000010101110 N
b1100000000010101110 m
b10101110 2
b10101110 M
b10101110 W
b101110 3
b101110 F
b101110 L
b110 $
b110 R
b110 [
b110 w
b10010011 d
b0 ;
b0 C
b0 U
b0 l
b110100000001100000000010101110 /
b110100000001100000000010101110 K
b110100000001100000000010101110 p
b110100000001100000000010101110 s
b100 *
b100 q
b100 r
1=
#10000
0=
#15000
b101000001 8
b101000001 \
b101000001 v
b101000001 9
b101000001 A
b101000001 T
b101000001 t
b100000000100001 0
b100000000100001 B
b100000000100001 Y
b100000000100001 n
b1000 #
b1000 ]
b1000 y
b10010011 <
b10010011 ?
b10010011 k
b0 7
b0 @
b0 G
1'
06
b11000 J
b11001100100000000100001 1
b11001100100000000100001 N
b11001100100000000100001 m
b100000000100001 2
b100000000100001 M
b100000000100001 W
b100001 3
b100001 F
b100001 L
b0 "
b0 S
b1000 (
b1000 P
b1000 x
b11 %
b11 Q
b11 Z
b0 +
b0 E
b0 O
b10101110 g
b10101110 ;
b10101110 C
b10101110 U
b10101110 l
b11001100100000000100001 /
b11001100100000000100001 K
b11001100100000000100001 p
b11001100100000000100001 s
b1000 *
b1000 q
b1000 r
1=
#20000
0=
#25000
b11111111111111111111111111100101 8
b11111111111111111111111111100101 \
b11111111111111111111111111100101 v
b100100000100011 0
b100100000100011 B
b100100000100011 Y
b100100000100011 n
b1001 #
b1001 ]
b1001 y
b11111111111111111111111111100101 9
b11111111111111111111111111100101 A
b11111111111111111111111111100101 T
b11111111111111111111111111100101 t
b1 7
b1 @
b1 G
b10000011000 J
b11001100100100000100011 1
b11001100100100000100011 N
b11001100100100000100011 m
b100100000100011 2
b100100000100011 M
b100100000100011 W
b100011 3
b100011 F
b100011 L
b1001 (
b1001 P
b1001 x
b101000001 i
b11001100100100000100011 /
b11001100100100000100011 K
b11001100100100000100011 p
b11001100100100000100011 s
b1100 *
b1100 q
b1100 r
1=
#30000
0=
#35000
b0 :
b0 >
b0 D
b11111111111111111111111111100101 8
b11111111111111111111111111100101 \
b11111111111111111111111111100101 v
b100001 0
b100001 B
b100001 Y
b100001 n
b0 #
b0 ]
b0 y
b0 ;
b0 C
b0 U
b0 l
b11111111111111111111111111100101 <
b11111111111111111111111111100101 ?
b11111111111111111111111111100101 k
b11111111111111111111111111100101 9
b11111111111111111111111111100101 A
b11111111111111111111111111100101 T
b11111111111111111111111111100101 t
b0 7
b0 @
b0 G
b11000 J
b1001010100000000000100001 1
b1001010100000000000100001 N
b1001010100000000000100001 m
b100001 2
b100001 M
b100001 W
b100001 3
b100001 F
b100001 L
b0 (
b0 P
b0 x
b1010 $
b1010 R
b1010 [
b1010 w
b1001 %
b1001 Q
b1001 Z
b11111111111111111111111111100101 j
b1001010100000000000100001 /
b1001010100000000000100001 K
b1001010100000000000100001 p
b1001010100000000000100001 s
b10000 *
b10000 q
b10000 r
1=
#40000
0=
#45000
b10000 8
b10000 \
b10000 v
b10000 9
b10000 A
b10000 T
b10000 t
b10000 :
b10000 >
b10000 D
b10000 0
b10000 B
b10000 Y
b10000 n
b11111111111111111111111111100101 ;
b11111111111111111111111111100101 C
b11111111111111111111111111100101 U
b11111111111111111111111111100101 l
b0 <
b0 ?
b0 k
b1 4
b1 H
b1 X
0&
16
1-
b100001110 J
b10010000000000010000 1
b10010000000000010000 N
b10010000000000010000 m
b10000 2
b10000 M
b10000 W
b10000 3
b10000 F
b10000 L
b1001 $
b1001 R
b1001 [
b1001 w
b0 %
b0 Q
b0 Z
b101011 +
b101011 E
b101011 O
b0 ^
b10101100000010010000000000010000 /
b10101100000010010000000000010000 K
b10101100000010010000000000010000 p
b10101100000010010000000000010000 s
b10100 *
b10100 q
b10100 r
1=
#50000
0=
#55000
b11111111111111111111111111100101 8
b11111111111111111111111111100101 \
b11111111111111111111111111100101 v
b0 ;
b0 C
b0 U
b0 l
b1010 #
b1010 ]
b1010 y
1&
0'
0-
1.
b100010101 J
b10100000000000010000 1
b10100000000000010000 N
b10100000000000010000 m
b1010 $
b1010 R
b1010 [
b1010 w
b100011 +
b100011 E
b100011 O
b11111111111111111111111111100101 5
b11111111111111111111111111100101 V
b11111111111111111111111111100101 u
b10001100000010100000000000010000 /
b10001100000010100000000000010000 K
b10001100000010100000000000010000 p
b10001100000010100000000000010000 s
b11000 *
b11000 q
b11000 r
1=
#60000
0=
#65000
1!
bx 5
bx V
bx u
b11111111111111111111111111100101 :
b11111111111111111111111111100101 >
b11111111111111111111111111100101 D
b0 8
b0 \
b0 v
b10 0
b10 B
b10 Y
b10 n
b11111111111111111111111111100101 <
b11111111111111111111111111100101 ?
b11111111111111111111111111100101 k
b0 9
b0 A
b0 T
b0 t
b1 7
b1 @
b1 G
b0 4
b0 H
b0 X
b1 ,
b1 I
b1 o
0&
06
0.
b10000100000 J
b1001010100000000000000010 1
b1001010100000000000000010 N
b1001010100000000000000010 m
b10 2
b10 M
b10 W
b10 3
b10 F
b10 L
b1001 %
b1001 Q
b1001 Z
b100 +
b100 E
b100 O
b11111111111111111111111111100101 `
b11111111111111111111111111100101 ;
b11111111111111111111111111100101 C
b11111111111111111111111111100101 U
b11111111111111111111111111100101 l
b10001001010100000000000000010 /
b10001001010100000000000000010 K
b10001001010100000000000000010 p
b10001001010100000000000000010 s
b11100 *
b11100 q
b11100 r
1=
#70000
0=
#75000
b1110111111101111 8
b1110111111101111 \
b1110111111101111 v
b1110111111101111 :
b1110111111101111 >
b1110111111101111 D
b1110111111101111 0
b1110111111101111 B
b1110111111101111 Y
b1110111111101111 n
b1011 #
b1011 ]
b1011 y
b0 ;
b0 C
b0 U
b0 l
b0 <
b0 ?
b0 k
0!
b1110111111101111 9
b1110111111101111 A
b1110111111101111 T
b1110111111101111 t
b11 7
b11 @
b11 G
b0 ,
b0 I
b0 o
1&
16
b110000010100 J
b10111110111111101111 1
b10111110111111101111 N
b10111110111111101111 m
b1110111111101111 2
b1110111111101111 M
b1110111111101111 W
b101111 3
b101111 F
b101111 L
b11111 "
b11111 S
b11101 (
b11101 P
b11101 x
b1011 $
b1011 R
b1011 [
b1011 w
b0 %
b0 Q
b0 Z
b1101 +
b1101 E
b1101 O
b110100000010111110111111101111 /
b110100000010111110111111101111 K
b110100000010111110111111101111 p
b110100000010111110111111101111 s
b101000 *
b101000 q
b101000 r
1=
#80000
0=
#85000
b1000101011001110000000000000000 8
b1000101011001110000000000000000 \
b1000101011001110000000000000000 v
b1000101011001110000000000000000 9
b1000101011001110000000000000000 A
b1000101011001110000000000000000 T
b1000101011001110000000000000000 t
b1000101011001110000000000000000 :
b1000101011001110000000000000000 >
b1000101011001110000000000000000 D
b1000101011001110000000000000000 0
b1000101011001110000000000000000 B
b1000101011001110000000000000000 Y
b1000101011001110000000000000000 n
b1001 #
b1001 ]
b1001 y
b0 7
b0 @
b0 G
b10 4
b10 H
b10 X
b1000010100 J
b10010100010101100111 1
b10010100010101100111 N
b10010100010101100111 m
b100010101100111 2
b100010101100111 M
b100010101100111 W
b100111 3
b100111 F
b100111 L
b10101 "
b10101 S
b1000 (
b1000 P
b1000 x
b1001 $
b1001 R
b1001 [
b1001 w
b1111 +
b1111 E
b1111 O
b1110111111101111 a
b11111111111111111111111111100101 ;
b11111111111111111111111111100101 C
b11111111111111111111111111100101 U
b11111111111111111111111111100101 l
b111100000010010100010101100111 /
b111100000010010100010101100111 K
b111100000010010100010101100111 p
b111100000010010100010101100111 s
b101100 *
b101100 q
b101100 r
1=
#90000
0=
#95000
b0 8
b0 \
b0 v
1!
b0 9
b0 A
b0 T
b0 t
b0 :
b0 >
b0 D
b110000000111 0
b110000000111 B
b110000000111 Y
b110000000111 n
b0 #
b0 ]
b0 y
b0 4
b0 H
b0 X
b10 ,
b10 I
b10 o
0&
06
b1000000 J
b110000000111 1
b110000000111 N
b110000000111 m
b110000000111 2
b110000000111 M
b110000000111 W
b111 3
b111 F
b111 L
b10000 "
b10000 S
b1 (
b1 P
b1 x
b0 $
b0 R
b0 [
b0 w
b10 +
b10 E
b10 O
b1000101011001110000000000000000 j
b0 ;
b0 C
b0 U
b0 l
b1000000000000000110000000111 /
b1000000000000000110000000111 K
b1000000000000000110000000111 p
b1000000000000000110000000111 s
b110000 *
b110000 q
b110000 r
1=
#100000
0=
#105000
bx 8
bx \
bx v
bx :
bx >
bx D
0!
bx 9
bx A
bx T
bx t
b0xxxxxxxxxxxxxxxx 0
b0xxxxxxxxxxxxxxxx B
b0xxxxxxxxxxxxxxxx Y
b0xxxxxxxxxxxxxxxx n
bx #
bx ]
bx y
bx ;
bx C
bx U
bx l
bx <
bx ?
bx k
b0 ,
b0 I
b0 o
b0 J
bx 1
bx N
bx m
bx 2
bx M
bx W
bx 3
bx F
bx L
bx "
bx S
bx (
bx P
bx x
bx $
bx R
bx [
bx w
bx %
bx Q
bx Z
bx +
bx E
bx O
bx /
bx K
bx p
bx s
b11000000011100 *
b11000000011100 q
b11000000011100 r
1=
#110000
0=
#115000
b11000000100000 *
b11000000100000 q
b11000000100000 r
1=
#120000
0=
#125000
b11000000100100 *
b11000000100100 q
b11000000100100 r
1=
#130000
0=
#135000
b11000000101000 *
b11000000101000 q
b11000000101000 r
1=
#140000
0=
#145000
b11000000101100 *
b11000000101100 q
b11000000101100 r
1=
#150000
0=
#155000
b11000000110000 *
b11000000110000 q
b11000000110000 r
1=
#160000
0=
#165000
b11000000110100 *
b11000000110100 q
b11000000110100 r
1=
#170000
0=
#175000
b11000000111000 *
b11000000111000 q
b11000000111000 r
1=
#180000
0=
#185000
b11000000111100 *
b11000000111100 q
b11000000111100 r
1=
#190000
0=
#195000
b11000001000000 *
b11000001000000 q
b11000001000000 r
1=
